LICENSE
MANIFEST.in
README.md
setup.cfg
setup.py
zohocrmsdk/__init__.py
zohocrmsdk/src/__init__.py
zohocrmsdk/src/json_details.json
zohocrmsdk/src/com/__init__.py
zohocrmsdk/src/com/zoho/__init__.py
zohocrmsdk/src/com/zoho/api/__init__.py
zohocrmsdk/src/com/zoho/api/authenticator/__init__.py
zohocrmsdk/src/com/zoho/api/authenticator/oauth_token.py
zohocrmsdk/src/com/zoho/api/authenticator/token.py
zohocrmsdk/src/com/zoho/api/authenticator/store/__init__.py
zohocrmsdk/src/com/zoho/api/authenticator/store/db_store.py
zohocrmsdk/src/com/zoho/api/authenticator/store/file_store.py
zohocrmsdk/src/com/zoho/api/authenticator/store/token_store.py
zohocrmsdk/src/com/zoho/api/logger/__init__.py
zohocrmsdk/src/com/zoho/api/logger/logger.py
zohocrmsdk/src/com/zoho/crm/__init__.py
zohocrmsdk/src/com/zoho/crm/api/__init__.py
zohocrmsdk/src/com/zoho/crm/api/header.py
zohocrmsdk/src/com/zoho/crm/api/header_map.py
zohocrmsdk/src/com/zoho/crm/api/initializer.py
zohocrmsdk/src/com/zoho/crm/api/param.py
zohocrmsdk/src/com/zoho/crm/api/parameter_map.py
zohocrmsdk/src/com/zoho/crm/api/request_proxy.py
zohocrmsdk/src/com/zoho/crm/api/sdk_config.py
zohocrmsdk/src/com/zoho/crm/api/user_signature.py
zohocrmsdk/src/com/zoho/crm/api/apis/__init__.py
zohocrmsdk/src/com/zoho/crm/api/apis/api_exception.py
zohocrmsdk/src/com/zoho/crm/api/apis/apis_operations.py
zohocrmsdk/src/com/zoho/crm/api/apis/operation_types.py
zohocrmsdk/src/com/zoho/crm/api/apis/response_handler.py
zohocrmsdk/src/com/zoho/crm/api/apis/response_wrapper.py
zohocrmsdk/src/com/zoho/crm/api/apis/supported_api.py
zohocrmsdk/src/com/zoho/crm/api/appointment_preference/__init__.py
zohocrmsdk/src/com/zoho/crm/api/appointment_preference/action_handler.py
zohocrmsdk/src/com/zoho/crm/api/appointment_preference/action_response.py
zohocrmsdk/src/com/zoho/crm/api/appointment_preference/action_wrapper.py
zohocrmsdk/src/com/zoho/crm/api/appointment_preference/api_exception.py
zohocrmsdk8_0.egg-info/PKG-INFO
zohocrmsdk8_0.egg-info/SOURCES.txt
zohocrmsdk8_0.egg-info/dependency_links.txt
zohocrmsdk8_0.egg-info/requires.txt
zohocrmsdk8_0.egg-info/top_level.txt