Metadata-Version: 2.1
Name: zohocrmsdk8_0
Version: 5.0.0
Summary: Zoho CRM SDK for ZOHO CRM v8 APIs
Home-page: https://github.com/zoho/zohocrm-python-sdk-8.0
Author: Zoho CRM API Team
Author-email: support@zohocrm.com
License: Apache Software License, Version 2.0, http://www.apache.org/licenses/LICENSE-2.0
Keywords: development,zoho,crm,api,zcrmsdk,zohocrmsdksdk,zcrm,zohocrmsdk8_0
Classifier: Development Status :: 5 - Production/Stable
Classifier: Intended Audience :: Developers
Classifier: License :: OSI Approved :: Apache Software License
Classifier: Topic :: Software Development :: Build Tools
Classifier: Programming Language :: Python :: 3
Classifier: Programming Language :: Python :: 3.3
Classifier: Programming Language :: Python :: 3.4
Classifier: Programming Language :: Python :: 3.5
Classifier: Programming Language :: Python :: 3.6
Classifier: Programming Language :: Python :: 3.7
Classifier: Programming Language :: Python :: 3.8
License-File: LICENSE
Requires-Dist: requests==2.32.4
Requires-Dist: python-dateutil
Requires-Dist: urllib3
Requires-Dist: setuptools
Provides-Extra: mysql
Requires-Dist: mysql-connector-python; extra == "mysql"
